codetell/__init__.py
codetell-0.1.1.dist-info/LICENSE
codetell-0.1.1.dist-info/METADATA
codetell-0.1.1.dist-info/WHEEL
codetell-0.1.1.dist-info/entry_points.txt
codetell-0.1.1.dist-info/top_level.txt
codetell-0.1.1.dist-info/RECORD
